geaicontext/__init__.py
geaicontext/context.py
geaicontext/testRetrieve.py
geaicontext/testSave.py
geaicontext/clients/__init__.py
geaicontext/clients/mongo_client.py
geaicontext/clients/redis_client.py
geaicontext/tools/__init__.py
geaicontext/tools/retrieve.py
geaicontext/tools/save.py
geaicontext-1.0.2.dist-info/METADATA
geaicontext-1.0.2.dist-info/WHEEL
geaicontext-1.0.2.dist-info/entry_points.txt
geaicontext-1.0.2.dist-info/top_level.txt
geaicontext-1.0.2.dist-info/RECORD
