Metadata-Version: 2.4
Name: geaicontext
Version: 1.0.2
Summary: Context and Memory MCP
Requires-Python: >=3.12
Requires-Dist: fastmcp>=2.14.0
Requires-Dist: motor>=3.7.1
Requires-Dist: redis>=7.1.0
